dynamics-0.5.1.data/scripts/Connection.py
dynamics-0.5.1.data/scripts/Entity.py
dynamics-0.5.1.data/scripts/Utils.py
dynamics-0.5.1.data/scripts/dynamics.py
dynamics-0.5.1.data/scripts/objects.py
objects/Connection.py
objects/Entity.py
objects/Utils.py
objects/__init__.py
dynamics-0.5.1.dist-info/LICENSE
dynamics-0.5.1.dist-info/METADATA
dynamics-0.5.1.dist-info/WHEEL
dynamics-0.5.1.dist-info/top_level.txt
dynamics-0.5.1.dist-info/RECORD
