Metadata-Version: 2.1
Name: dynamics
Version: 0.5.1
Summary: A pandas helper to interact with MS Dynamics
Home-page: https://github.com/shytikov/dynamics
Author: Alexey Shytikov
Author-email: alexey.shytikov@gmail.com
License: UNKNOWN
Platform: UNKNOWN
Classifier: Programming Language :: Python :: 3
Classifier: License :: OSI Approved :: MIT License
Classifier: Operating System :: OS Independent
Requires-Dist: adal
Requires-Dist: pandas
Requires-Dist: requests
